[
  {
    "case_number": "I-200-23258-350616",
    "case_status": "Certified",
    "visa_class": "H-1B",
    "decision_date": "2023-09-22",
    "job_title": "Programmer Analyst",
    "soc_code": "15-1251.00",
    "soc_title": "Computer Programmers",
    "naics_code": "541511",
    "industry_label": "Custom Computer Programming Services",
    "state": "NC",
    "city": "Charlotte",
    "wage_usd": 100000.0,
    "prevailing_wage_usd": 93642.0,
    "worker_positions": 1,
    "fy": 2023
  },
  {
    "case_number": "I-200-23258-352459",
    "case_status": "Certified",
    "visa_class": "H-1B",
    "decision_date": "2023-09-22",
    "job_title": "Programmer Analyst ",
    "soc_code": "15-1251.00",
    "soc_title": "Computer Programmers",
    "naics_code": "541511",
    "industry_label": "Custom Computer Programming Services",
    "state": "TX",
    "city": "Irving",
    "wage_usd": 92000.0,
    "prevailing_wage_usd": 76731.0,
    "worker_positions": 1,
    "fy": 2023
  },
  {
    "case_number": "I-200-23179-152278",
    "case_status": "Certified",
    "visa_class": "H-1B",
    "decision_date": "2023-07-06",
    "job_title": "Systems Analyst ",
    "soc_code": "15-1211.00",
    "soc_title": "Computer Systems Analysts",
    "naics_code": "541511",
    "industry_label": "Custom Computer Programming Services",
    "state": "TX",
    "city": "Dallas",
    "wage_usd": 130000.0,
    "prevailing_wage_usd": 126402.0,
    "worker_positions": 1,
    "fy": 2023
  },
  {
    "case_number": "I-200-22263-482438",
    "case_status": "Certified",
    "visa_class": "H-1B",
    "decision_date": "2022-09-27",
    "job_title": "SYSTEMS ANALYST",
    "soc_code": "15-1211.00",
    "soc_title": "Computer Systems Analysts",
    "naics_code": "541511",
    "industry_label": "Custom Computer Programming Services",
    "state": "IL",
    "city": "VERNON HILLS",
    "wage_usd": 119628.0,
    "prevailing_wage_usd": 110344.0,
    "worker_positions": 1,
    "fy": 2022
  },
  {
    "case_number": "I-200-20253-812217",
    "case_status": "Certified - Withdrawn",
    "visa_class": "H-1B",
    "decision_date": "2022-09-09",
    "job_title": "PROGRAMMER ANALYST",
    "soc_code": "15-1131.00",
    "soc_title": "Computer Programmers",
    "naics_code": "541511",
    "industry_label": "Custom Computer Programming Services",
    "state": "IL",
    "city": "GLENVIEW",
    "wage_usd": 102072.0,
    "prevailing_wage_usd": 96450.0,
    "worker_positions": 1,
    "fy": 2022
  },
  {
    "case_number": "I-200-21022-028912",
    "case_status": "Certified - Withdrawn",
    "visa_class": "H-1B",
    "decision_date": "2022-09-09",
    "job_title": "PROGRAMMER ANALYST",
    "soc_code": "15-1131.00",
    "soc_title": "Computer Programmers",
    "naics_code": "541511",
    "industry_label": "Custom Computer Programming Services",
    "state": "NY",
    "city": "LEVITTOWN",
    "wage_usd": 100000.0,
    "prevailing_wage_usd": 98072.0,
    "worker_positions": 1,
    "fy": 2022
  },
  {
    "case_number": "I-200-21313-694874",
    "case_status": "Certified - Withdrawn",
    "visa_class": "H-1B",
    "decision_date": "2022-09-09",
    "job_title": "Systems Analyst",
    "soc_code": "15-1121.00",
    "soc_title": "Computer Systems Analysts",
    "naics_code": "541511",
    "industry_label": "Custom Computer Programming Services",
    "state": "TX",
    "city": "IRVING",
    "wage_usd": 90850.0,
    "prevailing_wage_usd": 85301.0,
    "worker_positions": 1,
    "fy": 2022
  },
  {
    "case_number": "I-200-21309-690526",
    "case_status": "Certified - Withdrawn",
    "visa_class": "H-1B",
    "decision_date": "2022-09-02",
    "job_title": "SYSTEMS ANALYST ",
    "soc_code": "15-1121.00",
    "soc_title": "Computer Systems Analysts",
    "naics_code": "541511",
    "industry_label": "Custom Computer Programming Services",
    "state": "KY",
    "city": "LOUISVILLE",
    "wage_usd": 82000.0,
    "prevailing_wage_usd": 70533.0,
    "worker_positions": 1,
    "fy": 2022
  },
  {
    "case_number": "I-200-22221-406593",
    "case_status": "Certified",
    "visa_class": "H-1B",
    "decision_date": "2022-08-16",
    "job_title": "SYSTEMS ANALYST",
    "soc_code": "15-1211.00",
    "soc_title": "Computer Systems Analysts",
    "naics_code": "541511",
    "industry_label": "Custom Computer Programming Services",
    "state": "TX",
    "city": "AUSTIN",
    "wage_usd": 109755.0,
    "prevailing_wage_usd": 100693.0,
    "worker_positions": 1,
    "fy": 2022
  },
  {
    "case_number": "I-200-22160-262273",
    "case_status": "Certified - Withdrawn",
    "visa_class": "H-1B",
    "decision_date": "2022-07-22",
    "job_title": "SYSTEMS ANALYST",
    "soc_code": "15-1199.01",
    "soc_title": "Software Quality Assurance Engineers and Testers",
    "naics_code": "541511",
    "industry_label": "Custom Computer Programming Services",
    "state": "AZ",
    "city": "CHANDLER ",
    "wage_usd": 109725.0,
    "prevailing_wage_usd": 102669.0,
    "worker_positions": 1,
    "fy": 2022
  },
  {
    "case_number": "I-200-22193-347674",
    "case_status": "Certified",
    "visa_class": "H-1B",
    "decision_date": "2022-07-19",
    "job_title": "QUALITY ASSURANCE ANALYST",
    "soc_code": "15-1253.00",
    "soc_title": "Software Quality Assurance Analysts and Testers",
    "naics_code": "541511",
    "industry_label": "Custom Computer Programming Services",
    "state": "AZ",
    "city": "CHANDLER",
    "wage_usd": 109725.0,
    "prevailing_wage_usd": 98218.0,
    "worker_positions": 1,
    "fy": 2022
  },
  {
    "case_number": "I-200-21256-579177",
    "case_status": "Certified",
    "visa_class": "H-1B",
    "decision_date": "2021-09-21",
    "job_title": "SYSTEMS ANALYST",
    "soc_code": "15-1121.00",
    "soc_title": "Computer Systems Analysts",
    "naics_code": "541511",
    "industry_label": "Custom Computer Programming Services",
    "state": "KY",
    "city": "LOUISVILLE",
    "wage_usd": 90000.0,
    "prevailing_wage_usd": 85467.0,
    "worker_positions": 1,
    "fy": 2021
  },
  {
    "case_number": "I-200-21257-583818",
    "case_status": "Certified",
    "visa_class": "H-1B",
    "decision_date": "2021-09-21",
    "job_title": "PROGRAMMER ANALYST",
    "soc_code": "15-1131.00",
    "soc_title": "Computer Programmers",
    "naics_code": "541511",
    "industry_label": "Custom Computer Programming Services",
    "state": "IL",
    "city": "ELK GROVE VILLAGE",
    "wage_usd": 103667.0,
    "prevailing_wage_usd": 103667.0,
    "worker_positions": 1,
    "fy": 2021
  },
  {
    "case_number": "I-200-21244-558697",
    "case_status": "Certified",
    "visa_class": "H-1B",
    "decision_date": "2021-09-09",
    "job_title": "SYSTEMS ANALYST",
    "soc_code": "15-1121.00",
    "soc_title": "Computer Systems Analysts",
    "naics_code": "541511",
    "industry_label": "Custom Computer Programming Services",
    "state": "NC",
    "city": "Charlotte",
    "wage_usd": 137343.0,
    "prevailing_wage_usd": 117874.0,
    "worker_positions": 1,
    "fy": 2021
  },
  {
    "case_number": "I-200-21243-557409",
    "case_status": "Certified",
    "visa_class": "H-1B",
    "decision_date": "2021-09-08",
    "job_title": "SYSTEMS ANALYST",
    "soc_code": "15-1121.00",
    "soc_title": "Computer Systems Analysts",
    "naics_code": "541511",
    "industry_label": "Custom Computer Programming Services",
    "state": "IL",
    "city": "VERNON HILLS",
    "wage_usd": 131865.0,
    "prevailing_wage_usd": 111197.0,
    "worker_positions": 1,
    "fy": 2021
  },
  {
    "case_number": "I-200-21244-557425",
    "case_status": "Certified",
    "visa_class": "H-1B",
    "decision_date": "2021-09-08",
    "job_title": "PROGRAMMER ANALYST",
    "soc_code": "15-1131.00",
    "soc_title": "Computer Programmers",
    "naics_code": "541511",
    "industry_label": "Custom Computer Programming Services",
    "state": "IL",
    "city": "ELK GROVE VILLAGE",
    "wage_usd": 107589.0,
    "prevailing_wage_usd": 103667.0,
    "worker_positions": 1,
    "fy": 2021
  },
  {
    "case_number": "I-200-21228-524734",
    "case_status": "Certified",
    "visa_class": "H-1B",
    "decision_date": "2021-08-23",
    "job_title": "Systems Analyst",
    "soc_code": "15-1121.00",
    "soc_title": "Computer Systems Analysts",
    "naics_code": "541511",
    "industry_label": "Custom Computer Programming Services",
    "state": "IL",
    "city": "Chicago",
    "wage_usd": 81000.0,
    "prevailing_wage_usd": 75982.0,
    "worker_positions": 1,
    "fy": 2021
  },
  {
    "case_number": "I-200-21191-455074",
    "case_status": "Certified",
    "visa_class": "H-1B",
    "decision_date": "2021-07-16",
    "job_title": "SYSTEMS ANALYST",
    "soc_code": "15-1121.00",
    "soc_title": "Computer Systems Analysts",
    "naics_code": "541511",
    "industry_label": "Custom Computer Programming Services",
    "state": "TX",
    "city": "IRVING",
    "wage_usd": 90000.0,
    "prevailing_wage_usd": 85301.0,
    "worker_positions": 1,
    "fy": 2021
  },
  {
    "case_number": "I-200-21175-425471",
    "case_status": "Certified - Withdrawn",
    "visa_class": "H-1B",
    "decision_date": "2021-07-15",
    "job_title": "SYSTEMS ANALYST",
    "soc_code": "15-1121.00",
    "soc_title": "Computer Systems Analysts",
    "naics_code": "541511",
    "industry_label": "Custom Computer Programming Services",
    "state": "TX",
    "city": "IRVING",
    "wage_usd": 81000.0,
    "prevailing_wage_usd": 80475.0,
    "worker_positions": 1,
    "fy": 2021
  },
  {
    "case_number": "I-200-21175-425549",
    "case_status": "Certified - Withdrawn",
    "visa_class": "H-1B",
    "decision_date": "2021-07-15",
    "job_title": "SYSTEMS ANALYST",
    "soc_code": "15-1121.00",
    "soc_title": "Computer Systems Analysts",
    "naics_code": "541511",
    "industry_label": "Custom Computer Programming Services",
    "state": "TX",
    "city": "IRVING",
    "wage_usd": 90000.0,
    "prevailing_wage_usd": 80475.0,
    "worker_positions": 1,
    "fy": 2021
  },
  {
    "case_number": "I-200-20262-833604",
    "case_status": "Certified",
    "visa_class": "H-1B",
    "decision_date": "2020-09-25",
    "job_title": "SYSTEMS ANALYST",
    "soc_code": "15-1121.00",
    "soc_title": "Computer Systems Analysts",
    "naics_code": "541511",
    "industry_label": "Custom Computer Programming Services",
    "state": "IL",
    "city": "OAK BROOK",
    "wage_usd": 85000.0,
    "prevailing_wage_usd": 73882.0,
    "worker_positions": 1,
    "fy": 2020
  },
  {
    "case_number": "I-200-20253-812217",
    "case_status": "Certified",
    "visa_class": "H-1B",
    "decision_date": "2020-09-16",
    "job_title": "PROGRAMMER ANALYST",
    "soc_code": "15-1131.00",
    "soc_title": "Computer Programmers",
    "naics_code": "541511",
    "industry_label": "Custom Computer Programming Services",
    "state": "IL",
    "city": "GLENVIEW",
    "wage_usd": 102072.0,
    "prevailing_wage_usd": 96450.0,
    "worker_positions": 1,
    "fy": 2020
  },
  {
    "case_number": "I-200-20237-784042",
    "case_status": "Certified",
    "visa_class": "H-1B",
    "decision_date": "2020-08-31",
    "job_title": "SYSTEMS ANALYST",
    "soc_code": "15-1121.00",
    "soc_title": "Computer Systems Analysts",
    "naics_code": "541511",
    "industry_label": "Custom Computer Programming Services",
    "state": "NC",
    "city": "CHARLOTTE",
    "wage_usd": 84000.0,
    "prevailing_wage_usd": 80766.0,
    "worker_positions": 1,
    "fy": 2020
  },
  {
    "case_number": "I-200-20190-701993",
    "case_status": "Certified",
    "visa_class": "H-1B",
    "decision_date": "2020-07-15",
    "job_title": "SYSTEMS ANALYST",
    "soc_code": "15-1121.00",
    "soc_title": "Computer Systems Analysts",
    "naics_code": "541511",
    "industry_label": "Custom Computer Programming Services",
    "state": "IL",
    "city": "SCHAUMBURG",
    "wage_usd": 95000.0,
    "prevailing_wage_usd": 90709.0,
    "worker_positions": 1,
    "fy": 2020
  }
]
