[
  {
    "case_number": "I-200-25213-216670",
    "case_status": "Certified",
    "visa_class": "H-1B",
    "decision_date": "2025-08-08",
    "job_title": "Business Data Engineer",
    "soc_code": "15-1252.00",
    "soc_title": "Software Developers",
    "naics_code": "52411",
    "industry_label": "52411",
    "state": "TX",
    "city": "Frisco",
    "wage_usd": 90896.0,
    "prevailing_wage_usd": 90896.0,
    "worker_positions": 1,
    "fy": 2025
  },
  {
    "case_number": "I-200-25213-216826",
    "case_status": "Certified",
    "visa_class": "H-1B",
    "decision_date": "2025-08-08",
    "job_title": "Project Manager III",
    "soc_code": "15-1299.09",
    "soc_title": "Information Technology Project Managers",
    "naics_code": "52411",
    "industry_label": "52411",
    "state": "NE",
    "city": "Lincoln",
    "wage_usd": 111560.54,
    "prevailing_wage_usd": 56680.0,
    "worker_positions": 1,
    "fy": 2025
  },
  {
    "case_number": "I-200-25206-201416",
    "case_status": "Certified - Withdrawn",
    "visa_class": "H-1B",
    "decision_date": "2025-08-01",
    "job_title": "Project Manager II",
    "soc_code": "15-1299.09",
    "soc_title": "Information Technology Project Managers",
    "naics_code": "52411",
    "industry_label": "52411",
    "state": "NE",
    "city": "Lincoln",
    "wage_usd": 92339.0,
    "prevailing_wage_usd": 56680.0,
    "worker_positions": 1,
    "fy": 2025
  }
]
