[
  {
    "case_number": "I-200-20255-818711",
    "case_status": "Certified",
    "visa_class": "H-1B",
    "decision_date": "2020-09-18",
    "job_title": "BUSINESS INTELLIGENCE ANALYST",
    "soc_code": "15-1199.00",
    "soc_title": "Computer Occupations, All Other",
    "naics_code": "488510",
    "industry_label": "488510",
    "state": "FL",
    "city": "MIAMI",
    "wage_usd": 38000.0,
    "prevailing_wage_usd": 37149.0,
    "worker_positions": 1,
    "fy": 2020
  },
  {
    "case_number": "I-200-20255-818803",
    "case_status": "Certified",
    "visa_class": "H-1B",
    "decision_date": "2020-09-18",
    "job_title": "BUSINESS INTELLIGENCE ANALYST",
    "soc_code": "15-1199.00",
    "soc_title": "Computer Occupations, All Other",
    "naics_code": "488510",
    "industry_label": "488510",
    "state": "FL",
    "city": "MIAMI",
    "wage_usd": 58000.0,
    "prevailing_wage_usd": 57741.0,
    "worker_positions": 1,
    "fy": 2020
  }
]
