[
  {
    "case_number": "I-200-20238-786205",
    "case_status": "Certified",
    "visa_class": "H-1B",
    "decision_date": "2020-09-01",
    "job_title": "COMPUTER SYSTEMS ANALYST",
    "soc_code": "15-1121.00",
    "soc_title": "Computer Systems Analysts",
    "naics_code": "541512",
    "industry_label": "Computer Systems Design Services",
    "state": "MA",
    "city": "Boston",
    "wage_usd": 200000.0,
    "prevailing_wage_usd": 115398.0,
    "worker_positions": 1,
    "fy": 2020
  },
  {
    "case_number": "I-200-20238-787266",
    "case_status": "Certified",
    "visa_class": "H-1B",
    "decision_date": "2020-09-01",
    "job_title": "COMPUTER SYSTEMS ANALYST",
    "soc_code": "15-1121.00",
    "soc_title": "Computer Systems Analysts",
    "naics_code": "541512",
    "industry_label": "Computer Systems Design Services",
    "state": "MA",
    "city": "Boston",
    "wage_usd": 200000.0,
    "prevailing_wage_usd": 115398.0,
    "worker_positions": 1,
    "fy": 2020
  },
  {
    "case_number": "I-200-20225-765424",
    "case_status": "Certified",
    "visa_class": "H-1B",
    "decision_date": "2020-08-19",
    "job_title": "Computer Systems Analysts",
    "soc_code": "15-1121.00",
    "soc_title": "Computer Systems Analysts",
    "naics_code": "541512",
    "industry_label": "Computer Systems Design Services",
    "state": "MA",
    "city": "Boston",
    "wage_usd": 160000.0,
    "prevailing_wage_usd": 115398.0,
    "worker_positions": 1,
    "fy": 2020
  },
  {
    "case_number": "I-200-20225-765454",
    "case_status": "Certified",
    "visa_class": "H-1B",
    "decision_date": "2020-08-19",
    "job_title": "COMPUTER SYSTEMS ANALYST",
    "soc_code": "15-1121.00",
    "soc_title": "Computer Systems Analysts",
    "naics_code": "541512",
    "industry_label": "Computer Systems Design Services",
    "state": "MA",
    "city": "Boston",
    "wage_usd": 160000.0,
    "prevailing_wage_usd": 115398.0,
    "worker_positions": 1,
    "fy": 2020
  },
  {
    "case_number": "I-200-20225-765697",
    "case_status": "Certified",
    "visa_class": "H-1B",
    "decision_date": "2020-08-19",
    "job_title": "Computer Systems Analysts",
    "soc_code": "15-1121.00",
    "soc_title": "Computer Systems Analysts",
    "naics_code": "541512",
    "industry_label": "Computer Systems Design Services",
    "state": "OH",
    "city": "Dublin",
    "wage_usd": 160000.0,
    "prevailing_wage_usd": 103563.0,
    "worker_positions": 1,
    "fy": 2020
  }
]
