[
  {
    "case_number": "I-200-25329-436761",
    "case_status": "Certified",
    "visa_class": "H-1B",
    "decision_date": "2025-12-03",
    "job_title": "SMTS, Software Engineer & Data Science",
    "soc_code": "15-2051.00",
    "soc_title": "Data Scientists",
    "naics_code": "33591",
    "industry_label": "33591",
    "state": "CA",
    "city": "San Jose",
    "wage_usd": 174304.0,
    "prevailing_wage_usd": 174304.0,
    "worker_positions": 1,
    "fy": 2026
  },
  {
    "case_number": "I-200-25322-418608",
    "case_status": "Certified",
    "visa_class": "H-1B",
    "decision_date": "2025-11-25",
    "job_title": "SMTS, Separator Engineering & Process Development",
    "soc_code": "17-2131.00",
    "soc_title": "Materials Engineers",
    "naics_code": "33591",
    "industry_label": "33591",
    "state": "CA",
    "city": "San Jose",
    "wage_usd": 155251.0,
    "prevailing_wage_usd": 155251.0,
    "worker_positions": 1,
    "fy": 2026
  },
  {
    "case_number": "I-200-25316-399175",
    "case_status": "Certified",
    "visa_class": "H-1B",
    "decision_date": "2025-11-18",
    "job_title": "PMTS, Systems Engineer",
    "soc_code": "17-2199.05",
    "soc_title": "Mechatronics Engineers",
    "naics_code": "33591",
    "industry_label": "33591",
    "state": "CA",
    "city": "San Jose",
    "wage_usd": 187762.0,
    "prevailing_wage_usd": 187762.0,
    "worker_positions": 1,
    "fy": 2026
  },
  {
    "case_number": "I-200-24122-947573",
    "case_status": "Certified - Withdrawn",
    "visa_class": "H-1B",
    "decision_date": "2025-08-29",
    "job_title": "MTS, Industrial Engineer",
    "soc_code": "17-2112.00",
    "soc_title": "Industrial Engineers",
    "naics_code": "33591",
    "industry_label": "33591",
    "state": "CA",
    "city": "San Jose",
    "wage_usd": 89606.0,
    "prevailing_wage_usd": 89606.0,
    "worker_positions": 1,
    "fy": 2025
  },
  {
    "case_number": "I-200-22307-565900",
    "case_status": "Certified - Withdrawn",
    "visa_class": "H-1B",
    "decision_date": "2025-08-13",
    "job_title": "Sr. SAP Basis Administrator",
    "soc_code": "15-1242.00",
    "soc_title": "Database Administrators",
    "naics_code": "33591",
    "industry_label": "33591",
    "state": "CA",
    "city": "San Jose",
    "wage_usd": 185000.0,
    "prevailing_wage_usd": 91624.0,
    "worker_positions": 1,
    "fy": 2025
  },
  {
    "case_number": "I-200-25205-196463",
    "case_status": "Certified",
    "visa_class": "H-1B",
    "decision_date": "2025-07-30",
    "job_title": "SMTS, SW/Controls Engineer",
    "soc_code": "17-2199.05",
    "soc_title": "Mechatronics Engineers",
    "naics_code": "33591",
    "industry_label": "33591",
    "state": "CA",
    "city": "San Jose",
    "wage_usd": 129459.0,
    "prevailing_wage_usd": 129459.0,
    "worker_positions": 1,
    "fy": 2025
  },
  {
    "case_number": "I-200-25193-170724",
    "case_status": "Certified",
    "visa_class": "H-1B",
    "decision_date": "2025-07-18",
    "job_title": "Sr. Financial Analyst",
    "soc_code": "13-2051.00",
    "soc_title": "Financial and Investment Analysts",
    "naics_code": "33591",
    "industry_label": "33591",
    "state": "CA",
    "city": "San Jose",
    "wage_usd": 154336.0,
    "prevailing_wage_usd": 154336.0,
    "worker_positions": 1,
    "fy": 2025
  },
  {
    "case_number": "I-200-25184-152408",
    "case_status": "Certified",
    "visa_class": "H-1B",
    "decision_date": "2025-07-11",
    "job_title": "MTS, Manufacturing Process & Equipment Engineer",
    "soc_code": "17-2112.03",
    "soc_title": "Manufacturing Engineers",
    "naics_code": "33591",
    "industry_label": "33591",
    "state": "CA",
    "city": "San Jose",
    "wage_usd": 120182.0,
    "prevailing_wage_usd": 120182.0,
    "worker_positions": 1,
    "fy": 2025
  },
  {
    "case_number": "I-200-23059-811750",
    "case_status": "Certified - Withdrawn",
    "visa_class": "H-1B",
    "decision_date": "2025-07-01",
    "job_title": "Sr. Network Engineer",
    "soc_code": "15-1241.00",
    "soc_title": "Computer Network Architects",
    "naics_code": "33591",
    "industry_label": "33591",
    "state": "CA",
    "city": "San Jose",
    "wage_usd": 177320.0,
    "prevailing_wage_usd": 177320.0,
    "worker_positions": 1,
    "fy": 2025
  },
  {
    "case_number": "I-200-24242-303786",
    "case_status": "Certified - Withdrawn",
    "visa_class": "H-1B",
    "decision_date": "2025-07-01",
    "job_title": "PMTS, Security Engineer",
    "soc_code": "15-1212.00",
    "soc_title": "Information Security Analysts",
    "naics_code": "33591",
    "industry_label": "33591",
    "state": "CA",
    "city": "San Diego",
    "wage_usd": 202134.0,
    "prevailing_wage_usd": 202134.0,
    "worker_positions": 1,
    "fy": 2025
  },
  {
    "case_number": "I-200-23102-927997",
    "case_status": "Certified - Withdrawn",
    "visa_class": "H-1B",
    "decision_date": "2024-09-24",
    "job_title": "Battery Manufacturing Process Engineer",
    "soc_code": "17-2112.00",
    "soc_title": "Industrial Engineers",
    "naics_code": "33591",
    "industry_label": "33591",
    "state": "CA",
    "city": "San Jose",
    "wage_usd": 104000.0,
    "prevailing_wage_usd": 104000.0,
    "worker_positions": 1,
    "fy": 2024
  },
  {
    "case_number": "I-200-24250-320070",
    "case_status": "Certified",
    "visa_class": "H-1B",
    "decision_date": "2024-09-13",
    "job_title": "Principal Software and Controls Engineer",
    "soc_code": "17-2071.00",
    "soc_title": "Electrical Engineers",
    "naics_code": "33591",
    "industry_label": "33591",
    "state": "CA",
    "city": "San Jose",
    "wage_usd": 213595.0,
    "prevailing_wage_usd": 213595.0,
    "worker_positions": 1,
    "fy": 2024
  },
  {
    "case_number": "I-200-22157-249737",
    "case_status": "Certified - Withdrawn",
    "visa_class": "H-1B",
    "decision_date": "2024-09-10",
    "job_title": "MTS, Analytical & Characterization Engineer",
    "soc_code": "19-2032.00",
    "soc_title": "Materials Scientists",
    "naics_code": "33591",
    "industry_label": "33591",
    "state": "CA",
    "city": "San Jose",
    "wage_usd": 120000.0,
    "prevailing_wage_usd": 107744.0,
    "worker_positions": 1,
    "fy": 2024
  },
  {
    "case_number": "I-200-24242-303786",
    "case_status": "Certified",
    "visa_class": "H-1B",
    "decision_date": "2024-09-06",
    "job_title": "PMTS, Security Engineer",
    "soc_code": "15-1212.00",
    "soc_title": "Information Security Analysts",
    "naics_code": "33591",
    "industry_label": "33591",
    "state": "CA",
    "city": "San Diego",
    "wage_usd": 202134.0,
    "prevailing_wage_usd": 202134.0,
    "worker_positions": 1,
    "fy": 2024
  },
  {
    "case_number": "I-200-24242-303974",
    "case_status": "Certified",
    "visa_class": "H-1B",
    "decision_date": "2024-09-06",
    "job_title": "Sr. MTS, Metrology and Tooling Lead",
    "soc_code": "17-2141.00",
    "soc_title": "Mechanical Engineers",
    "naics_code": "33591",
    "industry_label": "33591",
    "state": "CA",
    "city": "San Jose",
    "wage_usd": 155043.0,
    "prevailing_wage_usd": 155043.0,
    "worker_positions": 1,
    "fy": 2024
  },
  {
    "case_number": "I-200-24236-291082",
    "case_status": "Certified",
    "visa_class": "H-1B",
    "decision_date": "2024-08-30",
    "job_title": "PMTS, Principal Software Engineer",
    "soc_code": "15-1252.00",
    "soc_title": "Software Developers",
    "naics_code": "33591",
    "industry_label": "33591",
    "state": "CA",
    "city": "Calabasas",
    "wage_usd": 176134.0,
    "prevailing_wage_usd": 176134.0,
    "worker_positions": 1,
    "fy": 2024
  },
  {
    "case_number": "I-200-24214-238902",
    "case_status": "Certified",
    "visa_class": "H-1B",
    "decision_date": "2024-08-08",
    "job_title": "Principal Member of Technical Staff, SW/Controls Engineer",
    "soc_code": "17-2199.05",
    "soc_title": "Mechatronics Engineers",
    "naics_code": "33591",
    "industry_label": "33591",
    "state": "CA",
    "city": "San Jose",
    "wage_usd": 179858.0,
    "prevailing_wage_usd": 179858.0,
    "worker_positions": 1,
    "fy": 2024
  },
  {
    "case_number": "I-200-24201-209186",
    "case_status": "Certified",
    "visa_class": "H-1B",
    "decision_date": "2024-07-26",
    "job_title": "Network Security Engineer",
    "soc_code": "15-1241.00",
    "soc_title": "Computer Network Architects",
    "naics_code": "33591",
    "industry_label": "33591",
    "state": "CA",
    "city": "San Jose",
    "wage_usd": 186472.0,
    "prevailing_wage_usd": 186472.0,
    "worker_positions": 1,
    "fy": 2024
  },
  {
    "case_number": "I-200-24102-878905",
    "case_status": "Certified - Withdrawn",
    "visa_class": "H-1B",
    "decision_date": "2024-07-22",
    "job_title": "MTS, Industrial Engineer",
    "soc_code": "17-2112.00",
    "soc_title": "Industrial Engineers",
    "naics_code": "33591",
    "industry_label": "33591",
    "state": "CA",
    "city": "San Jose",
    "wage_usd": 89606.0,
    "prevailing_wage_usd": 89606.0,
    "worker_positions": 1,
    "fy": 2024
  },
  {
    "case_number": "I-200-24178-151083",
    "case_status": "Certified",
    "visa_class": "H-1B",
    "decision_date": "2024-07-03",
    "job_title": "SMTS, Product Engineer",
    "soc_code": "17-2131.00",
    "soc_title": "Materials Engineers",
    "naics_code": "33591",
    "industry_label": "33591",
    "state": "CA",
    "city": "San Jose",
    "wage_usd": 136739.0,
    "prevailing_wage_usd": 136739.0,
    "worker_positions": 1,
    "fy": 2024
  },
  {
    "case_number": "I-200-23102-928020",
    "case_status": "Certified - Withdrawn",
    "visa_class": "H-1B",
    "decision_date": "2023-09-26",
    "job_title": "Data Automation Engineering, Manufacturing Operations",
    "soc_code": "17-2199.05",
    "soc_title": "Mechatronics Engineers",
    "naics_code": "33591",
    "industry_label": "33591",
    "state": "CA",
    "city": "San Jose",
    "wage_usd": 114192.0,
    "prevailing_wage_usd": 114192.0,
    "worker_positions": 1,
    "fy": 2023
  },
  {
    "case_number": "I-200-22160-260412",
    "case_status": "Certified - Withdrawn",
    "visa_class": "H-1B",
    "decision_date": "2023-09-18",
    "job_title": "Sr. Member of the Technical Staff, Metrology Pilot Line",
    "soc_code": "17-2071.00",
    "soc_title": "Electrical Engineers",
    "naics_code": "33591",
    "industry_label": "33591",
    "state": "CA",
    "city": "San Jose",
    "wage_usd": 160000.0,
    "prevailing_wage_usd": 126131.0,
    "worker_positions": 1,
    "fy": 2023
  },
  {
    "case_number": "I-200-23241-304970",
    "case_status": "Certified",
    "visa_class": "H-1B",
    "decision_date": "2023-09-06",
    "job_title": "Senior Member of Technical Staff",
    "soc_code": "17-2131.00",
    "soc_title": "Materials Engineers",
    "naics_code": "33591",
    "industry_label": "33591",
    "state": "CA",
    "city": "San Jose",
    "wage_usd": 136739.0,
    "prevailing_wage_usd": 136739.0,
    "worker_positions": 1,
    "fy": 2023
  },
  {
    "case_number": "I-202-22108-079972",
    "case_status": "Certified - Withdrawn",
    "visa_class": "H-1B1 Singapore",
    "decision_date": "2023-09-05",
    "job_title": "Principal Member of Technical Staff, Metrology Pilot Line",
    "soc_code": "19-2032.00",
    "soc_title": "Materials Scientists",
    "naics_code": "33591",
    "industry_label": "33591",
    "state": "CA",
    "city": "San Jose",
    "wage_usd": 195000.0,
    "prevailing_wage_usd": 141211.0,
    "worker_positions": 1,
    "fy": 2023
  },
  {
    "case_number": "I-200-23226-262726",
    "case_status": "Certified",
    "visa_class": "H-1B",
    "decision_date": "2023-08-21",
    "job_title": "Member of Technical Staff, Mechanical Design Engineer ",
    "soc_code": "17-2141.00",
    "soc_title": "Mechanical Engineers",
    "naics_code": "33591",
    "industry_label": "33591",
    "state": "CA",
    "city": "San Jose",
    "wage_usd": 116730.0,
    "prevailing_wage_usd": 116730.0,
    "worker_positions": 1,
    "fy": 2023
  },
  {
    "case_number": "I-200-23226-262759",
    "case_status": "Certified",
    "visa_class": "H-1B",
    "decision_date": "2023-08-21",
    "job_title": "Principal Member Technical Staff, Controls Vision Engineer ",
    "soc_code": "17-2199.05",
    "soc_title": "Mechatronics Engineers",
    "naics_code": "33591",
    "industry_label": "33591",
    "state": "CA",
    "city": "San Jose",
    "wage_usd": 170539.0,
    "prevailing_wage_usd": 170539.0,
    "worker_positions": 1,
    "fy": 2023
  },
  {
    "case_number": "I-200-21232-534697",
    "case_status": "Certified - Withdrawn",
    "visa_class": "H-1B",
    "decision_date": "2022-09-23",
    "job_title": "Supply Manager ",
    "soc_code": "11-9199.04",
    "soc_title": "Supply Chain Managers",
    "naics_code": "33591",
    "industry_label": "33591",
    "state": "CA",
    "city": "San Jose",
    "wage_usd": 155480.0,
    "prevailing_wage_usd": 155480.0,
    "worker_positions": 1,
    "fy": 2022
  },
  {
    "case_number": "I-200-22216-395506",
    "case_status": "Certified - Withdrawn",
    "visa_class": "H-1B",
    "decision_date": "2022-09-19",
    "job_title": "Senior Member Technical Staff, Senior Electronic Engineer",
    "soc_code": "17-2071.00",
    "soc_title": "Electrical Engineers",
    "naics_code": "33591",
    "industry_label": "33591",
    "state": "CA",
    "city": "San Jose",
    "wage_usd": 147300.14,
    "prevailing_wage_usd": 124259.0,
    "worker_positions": 1,
    "fy": 2022
  },
  {
    "case_number": "I-200-22223-412564",
    "case_status": "Certified",
    "visa_class": "H-1B",
    "decision_date": "2022-08-18",
    "job_title": "Senior Financial Analyst",
    "soc_code": "13-2051.00",
    "soc_title": "Financial and Investment Analysts",
    "naics_code": "33591",
    "industry_label": "33591",
    "state": "CA",
    "city": "San Jose",
    "wage_usd": 150000.0,
    "prevailing_wage_usd": 132579.0,
    "worker_positions": 1,
    "fy": 2022
  },
  {
    "case_number": "I-200-22221-405549",
    "case_status": "Certified",
    "visa_class": "H-1B",
    "decision_date": "2022-08-16",
    "job_title": "Senior Member Technical Staff, Project Manager",
    "soc_code": "17-2071.00",
    "soc_title": "Electrical Engineers",
    "naics_code": "33591",
    "industry_label": "33591",
    "state": "CA",
    "city": "San Jose",
    "wage_usd": 160000.0,
    "prevailing_wage_usd": 148658.0,
    "worker_positions": 1,
    "fy": 2022
  },
  {
    "case_number": "I-200-22216-395435",
    "case_status": "Certified",
    "visa_class": "H-1B",
    "decision_date": "2022-08-10",
    "job_title": "Battery Cell Engineering Program Manager",
    "soc_code": "17-2141.00",
    "soc_title": "Mechanical Engineers",
    "naics_code": "33591",
    "industry_label": "33591",
    "state": "CA",
    "city": "San Jose",
    "wage_usd": 190000.0,
    "prevailing_wage_usd": 161886.0,
    "worker_positions": 1,
    "fy": 2022
  },
  {
    "case_number": "I-200-22216-395508",
    "case_status": "Certified",
    "visa_class": "H-1B",
    "decision_date": "2022-08-10",
    "job_title": "Senior Capacity Planner",
    "soc_code": "17-2112.00",
    "soc_title": "Industrial Engineers",
    "naics_code": "33591",
    "industry_label": "33591",
    "state": "CA",
    "city": "San Jose",
    "wage_usd": 185000.0,
    "prevailing_wage_usd": 104000.0,
    "worker_positions": 1,
    "fy": 2022
  },
  {
    "case_number": "I-200-21288-648119",
    "case_status": "Certified - Withdrawn",
    "visa_class": "H-1B",
    "decision_date": "2022-08-09",
    "job_title": "Project Manager, Metrology",
    "soc_code": "11-9041.00",
    "soc_title": "Architectural and Engineering Managers",
    "naics_code": "33591",
    "industry_label": "33591",
    "state": "CA",
    "city": "San Jose",
    "wage_usd": 190000.0,
    "prevailing_wage_usd": 189883.0,
    "worker_positions": 1,
    "fy": 2022
  },
  {
    "case_number": "I-200-22112-097614",
    "case_status": "Certified - Withdrawn",
    "visa_class": "H-1B",
    "decision_date": "2022-07-15",
    "job_title": "MTS, Analytical/ External Lab Collaboration Engineer",
    "soc_code": "19-2032.00",
    "soc_title": "Materials Scientists",
    "naics_code": "33591",
    "industry_label": "33591",
    "state": "CA",
    "city": "San Jose",
    "wage_usd": 118000.0,
    "prevailing_wage_usd": 107744.0,
    "worker_positions": 1,
    "fy": 2022
  },
  {
    "case_number": "I-200-22175-310739",
    "case_status": "Certified",
    "visa_class": "H-1B",
    "decision_date": "2022-07-01",
    "job_title": "Principal Member of Technical Staff",
    "soc_code": "17-2131.00",
    "soc_title": "Materials Engineers",
    "naics_code": "33591",
    "industry_label": "33591",
    "state": "CA",
    "city": "San Jose",
    "wage_usd": 161400.0,
    "prevailing_wage_usd": 119870.0,
    "worker_positions": 1,
    "fy": 2022
  },
  {
    "case_number": "I-200-21259-589230",
    "case_status": "Certified",
    "visa_class": "H-1B",
    "decision_date": "2021-09-23",
    "job_title": "Senior Process Engineer",
    "soc_code": "17-2041.00",
    "soc_title": "Chemical Engineers",
    "naics_code": "33591",
    "industry_label": "33591",
    "state": "CA",
    "city": "San Jose",
    "wage_usd": 142313.0,
    "prevailing_wage_usd": 116251.0,
    "worker_positions": 1,
    "fy": 2021
  },
  {
    "case_number": "I-200-21232-534697",
    "case_status": "Certified",
    "visa_class": "H-1B",
    "decision_date": "2021-08-26",
    "job_title": "Supply Manager ",
    "soc_code": "11-9199.04",
    "soc_title": "Supply Chain Managers",
    "naics_code": "33591",
    "industry_label": "33591",
    "state": "CA",
    "city": "San Jose",
    "wage_usd": 155480.0,
    "prevailing_wage_usd": 155480.0,
    "worker_positions": 1,
    "fy": 2021
  },
  {
    "case_number": "I-200-21230-531387",
    "case_status": "Certified",
    "visa_class": "H-1B",
    "decision_date": "2021-08-25",
    "job_title": "Senior Modeling and Simulation Engineer",
    "soc_code": "17-2141.00",
    "soc_title": "Mechanical Engineers",
    "naics_code": "33591",
    "industry_label": "33591",
    "state": "CA",
    "city": "San Jose",
    "wage_usd": 160000.0,
    "prevailing_wage_usd": 125757.0,
    "worker_positions": 1,
    "fy": 2021
  },
  {
    "case_number": "I-200-21228-525672",
    "case_status": "Certified",
    "visa_class": "H-1B",
    "decision_date": "2021-08-23",
    "job_title": "Member of Technical Staff",
    "soc_code": "19-2032.00",
    "soc_title": "Materials Scientists",
    "naics_code": "33591",
    "industry_label": "33591",
    "state": "CA",
    "city": "San Jose",
    "wage_usd": 95000.0,
    "prevailing_wage_usd": 91021.0,
    "worker_positions": 1,
    "fy": 2021
  },
  {
    "case_number": "I-200-21168-406375",
    "case_status": "Certified - Withdrawn",
    "visa_class": "H-1B",
    "decision_date": "2021-08-17",
    "job_title": "Senior Modeling and Simulation Engineer  ",
    "soc_code": "17-2141.00",
    "soc_title": "Mechanical Engineers",
    "naics_code": "33591",
    "industry_label": "33591",
    "state": "CA",
    "city": "San Jose",
    "wage_usd": 160000.0,
    "prevailing_wage_usd": 125653.0,
    "worker_positions": 1,
    "fy": 2021
  }
]
