[
  {
    "case_number": "I-200-25322-416790",
    "case_status": "Certified",
    "visa_class": "H-1B",
    "decision_date": "2025-11-25",
    "job_title": "Assistant Professor",
    "soc_code": "25-1071.00",
    "soc_title": "Health Specialties Teachers, Postsecondary",
    "naics_code": "611310",
    "industry_label": "Colleges Universities and Professional Schools",
    "state": "AL",
    "city": "Tuskegee",
    "wage_usd": 90614.25,
    "prevailing_wage_usd": 72080.0,
    "worker_positions": 1,
    "fy": 2026
  },
  {
    "case_number": "I-200-25237-265069",
    "case_status": "Certified",
    "visa_class": "H-1B",
    "decision_date": "2025-09-02",
    "job_title": "Assistant Professor",
    "soc_code": "25-1021.00",
    "soc_title": "Computer Science Teachers, Postsecondary",
    "naics_code": "611310",
    "industry_label": "Colleges Universities and Professional Schools",
    "state": "AL",
    "city": "Tuskegee",
    "wage_usd": 78830.0,
    "prevailing_wage_usd": 78830.0,
    "worker_positions": 1,
    "fy": 2025
  },
  {
    "case_number": "I-200-25199-186531",
    "case_status": "Certified",
    "visa_class": "H-1B",
    "decision_date": "2025-07-25",
    "job_title": "Assistant Professor",
    "soc_code": "25-1032.00",
    "soc_title": "Engineering Teachers, Postsecondary",
    "naics_code": "611310",
    "industry_label": "Colleges Universities and Professional Schools",
    "state": "AL",
    "city": "Tuskegee",
    "wage_usd": 70000.0,
    "prevailing_wage_usd": 60380.0,
    "worker_positions": 1,
    "fy": 2025
  },
  {
    "case_number": "I-200-25189-158336",
    "case_status": "Certified",
    "visa_class": "H-1B",
    "decision_date": "2025-07-15",
    "job_title": "Assistant Professor",
    "soc_code": "25-1032.00",
    "soc_title": "Engineering Teachers, Postsecondary",
    "naics_code": "611310",
    "industry_label": "Colleges Universities and Professional Schools",
    "state": "AL",
    "city": "Tuskegee",
    "wage_usd": 75000.0,
    "prevailing_wage_usd": 60380.0,
    "worker_positions": 1,
    "fy": 2025
  },
  {
    "case_number": "I-200-25189-159906",
    "case_status": "Certified",
    "visa_class": "H-1B",
    "decision_date": "2025-07-15",
    "job_title": "Assistant Professor",
    "soc_code": "25-1022.00",
    "soc_title": "Mathematical Science Teachers, Postsecondary",
    "naics_code": "611310",
    "industry_label": "Colleges Universities and Professional Schools",
    "state": "AL",
    "city": "Tuskegee",
    "wage_usd": 52350.0,
    "prevailing_wage_usd": 49880.0,
    "worker_positions": 1,
    "fy": 2025
  },
  {
    "case_number": "I-200-24235-286791",
    "case_status": "Certified",
    "visa_class": "H-1B",
    "decision_date": "2024-08-29",
    "job_title": "Assistant Professor",
    "soc_code": "25-1022.00",
    "soc_title": "Mathematical Science Teachers, Postsecondary",
    "naics_code": "611310",
    "industry_label": "Colleges Universities and Professional Schools",
    "state": "AL",
    "city": "Tuskegee",
    "wage_usd": 52500.0,
    "prevailing_wage_usd": 52350.0,
    "worker_positions": 1,
    "fy": 2024
  },
  {
    "case_number": "I-200-22255-466603",
    "case_status": "Certified",
    "visa_class": "H-1B",
    "decision_date": "2022-09-19",
    "job_title": "ASSISTANT PROFESSOR",
    "soc_code": "25-1071.00",
    "soc_title": "Health Specialties Teachers, Postsecondary",
    "naics_code": "611310",
    "industry_label": "Colleges Universities and Professional Schools",
    "state": "AL",
    "city": "TUSKEGEE",
    "wage_usd": 87550.0,
    "prevailing_wage_usd": 72563.0,
    "worker_positions": 1,
    "fy": 2022
  },
  {
    "case_number": "I-200-22213-388451",
    "case_status": "Certified",
    "visa_class": "H-1B",
    "decision_date": "2022-08-08",
    "job_title": "ASSISTANT PROFESSOR",
    "soc_code": "25-1022.00",
    "soc_title": "Mathematical Science Teachers, Postsecondary",
    "naics_code": "611310",
    "industry_label": "Colleges Universities and Professional Schools",
    "state": "AL",
    "city": "TUSKEGEE",
    "wage_usd": 47520.0,
    "prevailing_wage_usd": 47520.0,
    "worker_positions": 1,
    "fy": 2022
  },
  {
    "case_number": "I-203-22201-365096",
    "case_status": "Certified",
    "visa_class": "E-3 Australian",
    "decision_date": "2022-07-27",
    "job_title": "ASSISTANT PROFESSOR",
    "soc_code": "25-1032.00",
    "soc_title": "Engineering Teachers, Postsecondary",
    "naics_code": "611310",
    "industry_label": "Colleges Universities and Professional Schools",
    "state": "AL",
    "city": "TUSKEGEE INSTITUTE",
    "wage_usd": 84000.0,
    "prevailing_wage_usd": 81379.8,
    "worker_positions": 1,
    "fy": 2022
  },
  {
    "case_number": "I-200-22196-355495",
    "case_status": "Certified",
    "visa_class": "H-1B",
    "decision_date": "2022-07-22",
    "job_title": "ASSISTANT PROFESSOR",
    "soc_code": "25-1021.00",
    "soc_title": "Computer Science Teachers, Postsecondary",
    "naics_code": "611310",
    "industry_label": "Colleges Universities and Professional Schools",
    "state": "AL",
    "city": "TUSKEGEE INSTITUTE",
    "wage_usd": 70000.0,
    "prevailing_wage_usd": 51370.0,
    "worker_positions": 1,
    "fy": 2022
  },
  {
    "case_number": "I-200-22196-355667",
    "case_status": "Certified",
    "visa_class": "H-1B",
    "decision_date": "2022-07-22",
    "job_title": "ASSOCIATE PROFESSOR",
    "soc_code": "25-1052.00",
    "soc_title": "Chemistry Teachers, Postsecondary",
    "naics_code": "611310",
    "industry_label": "Colleges Universities and Professional Schools",
    "state": "AL",
    "city": "TUSKEGEE INSTITUTE",
    "wage_usd": 83312.0,
    "prevailing_wage_usd": 72940.0,
    "worker_positions": 1,
    "fy": 2022
  },
  {
    "case_number": "I-200-22193-346852",
    "case_status": "Certified",
    "visa_class": "H-1B",
    "decision_date": "2022-07-19",
    "job_title": "ASSISTANT PROFESSOR",
    "soc_code": "25-1021.00",
    "soc_title": "Computer Science Teachers, Postsecondary",
    "naics_code": "611310",
    "industry_label": "Colleges Universities and Professional Schools",
    "state": "AL",
    "city": "TUSKEGEE INSTITUTE",
    "wage_usd": 70000.0,
    "prevailing_wage_usd": 51370.0,
    "worker_positions": 1,
    "fy": 2022
  },
  {
    "case_number": "I-200-21207-483837",
    "case_status": "Certified",
    "visa_class": "H-1B",
    "decision_date": "2021-08-02",
    "job_title": "PLANNING AND EVALUATION MANAGER",
    "soc_code": "29-2099.00",
    "soc_title": "Health Technologists and Technicians, All Other",
    "naics_code": "611310",
    "industry_label": "Colleges Universities and Professional Schools",
    "state": "AL",
    "city": "Tuskegee Institute",
    "wage_usd": 49166.0,
    "prevailing_wage_usd": 38938.0,
    "worker_positions": 1,
    "fy": 2021
  },
  {
    "case_number": "I-200-20248-806689",
    "case_status": "Certified",
    "visa_class": "H-1B",
    "decision_date": "2020-09-14",
    "job_title": "Assistant Professor",
    "soc_code": "25-1199.00",
    "soc_title": "Postsecondary Teachers, All Other",
    "naics_code": "611310",
    "industry_label": "Colleges Universities and Professional Schools",
    "state": "AL",
    "city": "Tuskegee Institute",
    "wage_usd": 67000.0,
    "prevailing_wage_usd": 24069.96,
    "worker_positions": 1,
    "fy": 2020
  },
  {
    "case_number": "I-200-20204-729024",
    "case_status": "Certified",
    "visa_class": "H-1B",
    "decision_date": "2020-07-29",
    "job_title": "ASSOCIATE PROFESSOR",
    "soc_code": "25-1052.00",
    "soc_title": "Chemistry Teachers, Postsecondary",
    "naics_code": "611310",
    "industry_label": "Colleges Universities and Professional Schools",
    "state": "AL",
    "city": "TUSKEGEE",
    "wage_usd": 73326.0,
    "prevailing_wage_usd": 63140.0,
    "worker_positions": 1,
    "fy": 2020
  }
]
