[
  {
    "case_number": "I-201-25241-275653",
    "case_status": "Certified",
    "visa_class": "H-1B1 Chile",
    "decision_date": "2025-09-08",
    "job_title": "Assistant Operations Manager",
    "soc_code": "11-9013.00",
    "soc_title": "Farmers, Ranchers, and Other Agricultural Managers",
    "naics_code": "541690",
    "industry_label": "541690",
    "state": "NJ",
    "city": "GLASSBORO",
    "wage_usd": 80000.0,
    "prevailing_wage_usd": 58594.0,
    "worker_positions": 1,
    "fy": 2025
  },
  {
    "case_number": "I-201-24201-208906",
    "case_status": "Certified",
    "visa_class": "H-1B1 Chile",
    "decision_date": "2024-07-26",
    "job_title": "Operations & Logistics Supervisor-West Coast",
    "soc_code": "11-9013.00",
    "soc_title": "Farmers, Ranchers, and Other Agricultural Managers",
    "naics_code": "541690",
    "industry_label": "541690",
    "state": "CA",
    "city": "Bakersfield",
    "wage_usd": 80000.0,
    "prevailing_wage_usd": 79768.0,
    "worker_positions": 1,
    "fy": 2024
  },
  {
    "case_number": "I-201-22195-352573",
    "case_status": "Certified",
    "visa_class": "H-1B1 Chile",
    "decision_date": "2022-07-21",
    "job_title": "Operations and Logistics Supervisor ",
    "soc_code": "11-9013.00",
    "soc_title": "Farmers, Ranchers, and Other Agricultural Managers",
    "naics_code": "541690",
    "industry_label": "541690",
    "state": "NJ",
    "city": "Swedesboro",
    "wage_usd": 85000.0,
    "prevailing_wage_usd": 78728.0,
    "worker_positions": 1,
    "fy": 2022
  },
  {
    "case_number": "I-201-22194-349430",
    "case_status": "Certified",
    "visa_class": "H-1B1 Chile",
    "decision_date": "2022-07-20",
    "job_title": "Operations & Logistics Supervisor  - West Coast",
    "soc_code": "11-9013.00",
    "soc_title": "Farmers, Ranchers, and Other Agricultural Managers",
    "naics_code": "541690",
    "industry_label": "541690",
    "state": "CA",
    "city": "Bakersfield ",
    "wage_usd": 70000.0,
    "prevailing_wage_usd": 52333.0,
    "worker_positions": 1,
    "fy": 2022
  },
  {
    "case_number": "I-201-20225-765099",
    "case_status": "Certified",
    "visa_class": "H-1B1 Chile",
    "decision_date": "2020-08-19",
    "job_title": "Operations and Logistics Supervisor",
    "soc_code": "11-3071.03",
    "soc_title": "Logistics Managers",
    "naics_code": "541690",
    "industry_label": "541690",
    "state": "CA",
    "city": "Bakerfield",
    "wage_usd": 85000.0,
    "prevailing_wage_usd": 71406.0,
    "worker_positions": 1,
    "fy": 2020
  }
]
