[
  {
    "company_slug": "bush-industries",
    "company": "Bush Industries, Inc.",
    "date": "04/30/2026",
    "effective_date": "04/30/2026",
    "region": "PA",
    "city": null,
    "workers": 75,
    "source_id": "recJjHbMJMp8o0iT9",
    "id": "warn-bb47510438acbc52"
  },
  {
    "company_slug": "aerofarms-inc-rescinded",
    "company": "AeroFarms, Inc. - Rescinded",
    "date": "04/29/2026",
    "effective_date": "06/19/2026",
    "region": "VA",
    "city": null,
    "workers": 175,
    "source_id": "recAxu3kW2kYeQiew",
    "id": "warn-7947fd35eb8f138e"
  },
  {
    "company_slug": "aerofarms-inc-rescinded",
    "company": "AeroFarms, Inc. - Rescinded",
    "date": "04/29/2026",
    "effective_date": "06/18/2026",
    "region": "VA",
    "city": null,
    "workers": 175,
    "source_id": "recwvwGl3ESzRCBd4",
    "id": "warn-4e875b2327d4d1ab"
  },
  {
    "company_slug": "aerofarms-inc-rescinded",
    "company": "AeroFarms, Inc. - Rescinded",
    "date": "04/29/2026",
    "effective_date": "06/14/2026",
    "region": "VA",
    "city": null,
    "workers": 175,
    "source_id": "recr9Tfvl2gRiwOdt",
    "id": "warn-dbc2e82f4c38812f"
  },
  {
    "company_slug": "aerofarms-inc-rescinded",
    "company": "AeroFarms, Inc. - Rescinded",
    "date": "04/29/2026",
    "effective_date": "06/13/2026",
    "region": "VA",
    "city": null,
    "workers": 5,
    "source_id": "recF1jqaZmEI3CYXe",
    "id": "warn-aec484101d431958"
  },
  {
    "company_slug": "aerofarms-inc-rescinded",
    "company": "AeroFarms, Inc. - Rescinded",
    "date": "04/29/2026",
    "effective_date": "06/08/2026",
    "region": "VA",
    "city": null,
    "workers": 5,
    "source_id": "recjz9CpBHKsRV4we",
    "id": "warn-f8c04d411cc40f1c"
  },
  {
    "company_slug": "aerofarms-inc-rescinded",
    "company": "AeroFarms, Inc. - Rescinded",
    "date": "04/29/2026",
    "effective_date": "06/07/2026",
    "region": "VA",
    "city": null,
    "workers": 175,
    "source_id": "recv5Ot03U4KmoNjj",
    "id": "warn-f02dddb863a188d0"
  },
  {
    "company_slug": "aerofarms-inc-rescinded",
    "company": "AeroFarms, Inc. - Rescinded",
    "date": "04/29/2026",
    "effective_date": "05/30/2026",
    "region": "VA",
    "city": null,
    "workers": 175,
    "source_id": "reckw4VwoPQ8hHPLA",
    "id": "warn-c94a0372478654fc"
  },
  {
    "company_slug": "aerofarms-inc-rescinded",
    "company": "AeroFarms, Inc. - Rescinded",
    "date": "04/29/2026",
    "effective_date": "05/29/2026",
    "region": "VA",
    "city": null,
    "workers": 175,
    "source_id": "recG1q58tHUoJctTN",
    "id": "warn-7d95309b9df4d01b"
  },
  {
    "company_slug": "aerofarms-inc-rescinded",
    "company": "AeroFarms, Inc. - Rescinded",
    "date": "04/29/2026",
    "effective_date": "05/28/2026",
    "region": "VA",
    "city": null,
    "workers": 175,
    "source_id": "recpPRJYIXFf9s6mw",
    "id": "warn-75176942b2f4b209"
  },
  {
    "company_slug": "aerofarms-inc-rescinded",
    "company": "AeroFarms, Inc. - Rescinded",
    "date": "04/29/2026",
    "effective_date": "05/25/2026",
    "region": "VA",
    "city": null,
    "workers": 175,
    "source_id": "recT0idFW7Hv88Pqh",
    "id": "warn-2f4c91b8d3d60deb"
  },
  {
    "company_slug": "cbre-government-defense-services",
    "company": "CBRE Government & Defense Services",
    "date": "04/29/2026",
    "effective_date": "05/17/2026",
    "region": "MD",
    "city": null,
    "workers": 175,
    "source_id": "recuOz1TnJIBoksUr",
    "id": "warn-bc50c845178191a7"
  },
  {
    "company_slug": "yanfeng-international-automotive-technology-us-i",
    "company": "Yanfeng International Automotive Technology US I LLC",
    "date": "04/29/2026",
    "effective_date": "04/29/2026",
    "region": "TN",
    "city": null,
    "workers": 175,
    "source_id": "recXzU6YKLdjpzvT2",
    "id": "warn-706ad363981f8633"
  },
  {
    "company_slug": "northpoint-expeditionary-learning-academy",
    "company": "Northpoint Expeditionary Learning Academy",
    "date": "04/29/2026",
    "effective_date": "04/29/2026",
    "region": "AZ",
    "city": null,
    "workers": 30,
    "source_id": "recRYPe7Z8zdQAiXb",
    "id": "warn-21e932735cd0b88c"
  },
  {
    "company_slug": "benchmark",
    "company": "Benchmark",
    "date": "04/29/2026",
    "effective_date": "04/29/2026",
    "region": "AZ",
    "city": null,
    "workers": 75,
    "source_id": "recdnVVwDgSlgo1Dc",
    "id": "warn-94e375e034b99bfd"
  },
  {
    "company_slug": "milestone-technologies",
    "company": "Milestone Technologies Inc.",
    "date": "04/29/2026",
    "effective_date": "04/29/2026",
    "region": "UT",
    "city": null,
    "workers": 30,
    "source_id": "recKawvaORaXzU8If",
    "id": "warn-6993c4d7bf206856"
  },
  {
    "company_slug": "down-lite-internaional",
    "company": "Down-Lite Internaional Inc",
    "date": "04/28/2026",
    "effective_date": "06/19/2026",
    "region": "OH",
    "city": null,
    "workers": 175,
    "source_id": "recr1DHF3fujyOjFb",
    "id": "warn-57058ffd0e224d00"
  },
  {
    "company_slug": "update-gxo-logistics-supply-chain",
    "company": "UPDATE GXO Logistics Supply Chain, Inc",
    "date": "04/28/2026",
    "effective_date": "05/02/2026",
    "region": "OH",
    "city": null,
    "workers": 175,
    "source_id": "recJCw9wSqboFarj8",
    "id": "warn-48035b20a0ef3b32"
  },
  {
    "company_slug": "perrigo-company",
    "company": "Perrigo Company",
    "date": "04/28/2026",
    "effective_date": "04/28/2026",
    "region": "VT",
    "city": null,
    "workers": 175,
    "source_id": "rec3EyiG89I9beUT6",
    "id": "warn-070ac7488d40b204"
  },
  {
    "company_slug": "amazon",
    "company": "Amazon",
    "date": "04/28/2026",
    "effective_date": "04/28/2026",
    "region": "PA",
    "city": null,
    "workers": 750,
    "source_id": "recLSm4DBfcnTNmTI",
    "id": "warn-4bafc6328b7fd7a6"
  },
  {
    "company_slug": "amazon",
    "company": "Amazon",
    "date": "04/28/2026",
    "effective_date": "04/28/2026",
    "region": "NJ",
    "city": null,
    "workers": 5,
    "source_id": "recSUyqXEo1GmKsBy",
    "id": "warn-ca32ea241b9966a3"
  },
  {
    "company_slug": "msgr-bryan-walsh-childrens-village",
    "company": "Msgr. Bryan Walsh Children’s Village",
    "date": "04/27/2026",
    "effective_date": "05/31/2026",
    "region": "FL",
    "city": null,
    "workers": 75,
    "source_id": "recnAFwewcPVbkN5P",
    "id": "warn-4f144fff2fddbd81"
  },
  {
    "company_slug": "black-tiger-medical-transportation",
    "company": "Black Tiger Medical Transportation",
    "date": "04/27/2026",
    "effective_date": "05/29/2026",
    "region": "CA",
    "city": null,
    "workers": 75,
    "source_id": "recapjJpV0OlhkSJ6",
    "id": "warn-4eedbc5f7b86597c"
  },
  {
    "company_slug": "first-brands-group",
    "company": "First Brands Group, LLC",
    "date": "04/27/2026",
    "effective_date": "04/27/2026",
    "region": "MI",
    "city": null,
    "workers": 30,
    "source_id": "recBQeCVGiDhCmft5",
    "id": "warn-24bfba53b7c2e3c9"
  },
  {
    "company_slug": "hangry-joes",
    "company": "Hangry Joe's",
    "date": "04/27/2026",
    "effective_date": "04/27/2026",
    "region": "MN",
    "city": null,
    "workers": 5,
    "source_id": "recmjt0cRQ15NdKme",
    "id": "warn-60a1640bd77273fd"
  },
  {
    "company_slug": "hangry-joes",
    "company": "Hangry Joe's",
    "date": "04/27/2026",
    "effective_date": "04/27/2026",
    "region": "MN",
    "city": null,
    "workers": 5,
    "source_id": "recf00A664AHBq8W7",
    "id": "warn-f038edcb38fe667c"
  },
  {
    "company_slug": "fm-restaurants-hq",
    "company": "FM Restaurants HQ, LLC",
    "date": "04/26/2026",
    "effective_date": "04/30/2026",
    "region": "CA",
    "city": null,
    "workers": 30,
    "source_id": "recOBJU05F0j2djvt",
    "id": "warn-18027056a431502b"
  },
  {
    "company_slug": "blue-cross-blue-shield",
    "company": "Blue Cross Blue Shield",
    "date": "04/26/2026",
    "effective_date": "04/26/2026",
    "region": "NJ",
    "city": null,
    "workers": 175,
    "source_id": "rectoaWWDawYSTNQ4",
    "id": "warn-d57da8da07aee8cc"
  },
  {
    "company_slug": "third-drop-coffee",
    "company": "Third Drop Coffee",
    "date": "04/26/2026",
    "effective_date": "04/26/2026",
    "region": "MN",
    "city": null,
    "workers": 5,
    "source_id": "recEvG6YcckioDCoq",
    "id": "warn-ffcc93eaff5fe5c1"
  },
  {
    "company_slug": "update-first-brands-group-cuyahoga-4",
    "company": "UPDATE First Brands Group Cuyahoga 4",
    "date": "04/24/2026",
    "effective_date": "05/31/2026",
    "region": "OH",
    "city": null,
    "workers": 175,
    "source_id": "recspFtaeNpmUtr41",
    "id": "warn-82288660520463d6"
  },
  {
    "company_slug": "update-first-brands-group-wood",
    "company": "UPDATE First Brands Group Wood",
    "date": "04/24/2026",
    "effective_date": "05/31/2026",
    "region": "OH",
    "city": null,
    "workers": 375,
    "source_id": "recT7O1cnryhe3IOq",
    "id": "warn-c2dfe3c5ced746d1"
  },
  {
    "company_slug": "update-first-brands-group-seneca",
    "company": "UPDATE First Brands Group Seneca",
    "date": "04/24/2026",
    "effective_date": "05/31/2026",
    "region": "OH",
    "city": null,
    "workers": 375,
    "source_id": "recNNqhiH9x2j0WLW",
    "id": "warn-2f6e1f305be7666c"
  },
  {
    "company_slug": "bright-planet-solar",
    "company": "Bright Planet Solar, Inc.",
    "date": "04/24/2026",
    "effective_date": "04/24/2026",
    "region": "UT",
    "city": null,
    "workers": 75,
    "source_id": "recamcYW0chmHTxhy",
    "id": "warn-148153153515dbac"
  },
  {
    "company_slug": "battelle",
    "company": "Battelle",
    "date": "04/23/2026",
    "effective_date": "06/22/2026",
    "region": "CO",
    "city": null,
    "workers": 5,
    "source_id": "recwVw36mKjBYkdHj",
    "id": "warn-48938c14d800263f"
  },
  {
    "company_slug": "republic-national-distributing-company",
    "company": "Republic National Distributing Company",
    "date": "04/23/2026",
    "effective_date": "06/21/2026",
    "region": "MD",
    "city": null,
    "workers": 375,
    "source_id": "recjV7afeV2tEf0gi",
    "id": "warn-5c1deff90aecc2b5"
  },
  {
    "company_slug": "republic-national-distributing-company-llc-reyes-holdings-llc-san-antonio",
    "company": "Republic National Distributing Company, LLC (Reyes Holdings, L.L.C) San Antonio",
    "date": "04/23/2026",
    "effective_date": "06/21/2026",
    "region": "TX",
    "city": null,
    "workers": 375,
    "source_id": "recHP4Shj6yNkxswk",
    "id": "warn-9e369607dcd33952"
  },
  {
    "company_slug": "republic-national-distributing-company-llc-reyes-holdings-llc-houston",
    "company": "Republic National Distributing Company, LLC (Reyes Holdings, L.L.C) Houston",
    "date": "04/23/2026",
    "effective_date": "06/21/2026",
    "region": "TX",
    "city": null,
    "workers": 750,
    "source_id": "recKI6ICFm2p2bH2x",
    "id": "warn-e45b47d1091bfb2f"
  },
  {
    "company_slug": "republic-national-distributing-company-llc-reyes-holdings-llc-grand-prairie",
    "company": "Republic National Distributing Company, LLC (Reyes Holdings, L.L.C) Grand Prairie",
    "date": "04/23/2026",
    "effective_date": "06/21/2026",
    "region": "TX",
    "city": null,
    "workers": 750,
    "source_id": "recr14h1eTDqvqSGa",
    "id": "warn-dcf11b5f4ea2f3cc"
  },
  {
    "company_slug": "republic-national-distributing-company-llc-reyes-holdings-llc-corpus-christie",
    "company": "Republic National Distributing Company, LLC (Reyes Holdings, L.L.C) Corpus Christie",
    "date": "04/23/2026",
    "effective_date": "06/21/2026",
    "region": "TX",
    "city": null,
    "workers": 75,
    "source_id": "rec3xt0NK6HO9Oqck",
    "id": "warn-57048e4e4b1894ce"
  },
  {
    "company_slug": "republic-national-distributing-company-llc-reyes-holdings-llc-austin",
    "company": "Republic National Distributing Company, LLC (Reyes Holdings, L.L.C) Austin",
    "date": "04/23/2026",
    "effective_date": "06/21/2026",
    "region": "TX",
    "city": null,
    "workers": 175,
    "source_id": "recoTWP5Mk856eW5p",
    "id": "warn-c7f02965e98b5d6a"
  },
  {
    "company_slug": "republic-national-distributing-company",
    "company": "Republic National Distributing Company",
    "date": "04/23/2026",
    "effective_date": "06/21/2026",
    "region": "DC",
    "city": null,
    "workers": 175,
    "source_id": "recK378Y7n1qsrVtG",
    "id": "warn-0f71ed21166ba307"
  },
  {
    "company_slug": "republic-national-distributing-company",
    "company": "Republic National Distributing Company",
    "date": "04/23/2026",
    "effective_date": "06/21/2026",
    "region": "VA",
    "city": null,
    "workers": 375,
    "source_id": "recXfHPFhWkAIw3S4",
    "id": "warn-da4b5b6f1f21bac9"
  },
  {
    "company_slug": "republic-national-distributing-company",
    "company": "Republic National Distributing Company",
    "date": "04/23/2026",
    "effective_date": "06/07/2026",
    "region": "SC",
    "city": null,
    "workers": 375,
    "source_id": "recx30zLwoWpGwWRC",
    "id": "warn-28ce7f217b26b7be"
  },
  {
    "company_slug": "epic-games-inc-remote-employees-in-el-segundo",
    "company": "Epic Games Inc. (Remote Employees in El Segundo)",
    "date": "04/23/2026",
    "effective_date": "03/27/2026",
    "region": "CA",
    "city": null,
    "workers": 5,
    "source_id": "recrmk1Foznpn1QyK",
    "id": "warn-d299298c211b95aa"
  },
  {
    "company_slug": "epic-games-inc-remote-employees-in-los-angeles",
    "company": "Epic Games Inc. (Remote Employees in Los Angeles)",
    "date": "04/23/2026",
    "effective_date": "03/27/2026",
    "region": "CA",
    "city": null,
    "workers": 75,
    "source_id": "recjr5yFEIBRSu7sr",
    "id": "warn-913928ee44589fcd"
  },
  {
    "company_slug": "epic-games-inc-remote-employees-in-san-francisco",
    "company": "Epic Games Inc. (Remote Employees in San Francisco)",
    "date": "04/23/2026",
    "effective_date": "03/27/2026",
    "region": "CA",
    "city": null,
    "workers": 30,
    "source_id": "rec2OmiGoX6A9grqw",
    "id": "warn-9b6be2745e2cc5c3"
  },
  {
    "company_slug": "epic-games",
    "company": "Epic Games Inc.",
    "date": "04/23/2026",
    "effective_date": "03/27/2026",
    "region": "CA",
    "city": null,
    "workers": 30,
    "source_id": "recQABj971fj7ZBS3",
    "id": "warn-b8be82d586931ce8"
  },
  {
    "company_slug": "epic-games",
    "company": "Epic Games Inc.",
    "date": "04/23/2026",
    "effective_date": "03/27/2026",
    "region": "CA",
    "city": null,
    "workers": 30,
    "source_id": "rechodCd22rhjICli",
    "id": "warn-598dcfad241fda8c"
  },
  {
    "company_slug": "republic-national-distributing-company",
    "company": "Republic National Distributing Company",
    "date": "04/23/2026",
    "effective_date": "04/23/2026",
    "region": "AZ",
    "city": null,
    "workers": 175,
    "source_id": "recNNgSmKFHtvsfvZ",
    "id": "warn-b3fc5dea52732ed2"
  },
  {
    "company_slug": "anna-maria-college",
    "company": "Anna Maria College",
    "date": "04/23/2026",
    "effective_date": "04/23/2026",
    "region": "MA",
    "city": null,
    "workers": 175,
    "source_id": "recef9EXUaSZGuu5V",
    "id": "warn-a2a2c3ea329fe9e0"
  }
]
