[
  {
    "company_slug": "sequel-youth-services-of-clarinda",
    "company": "Sequel Youth Services of Clarinda, LLC",
    "date": "02/03/2021",
    "effective_date": "03/05/2021",
    "region": "IA",
    "city": null,
    "workers": 75,
    "source_id": "rec0Srn2oOozOSyT3",
    "id": "warn-b5319677fa0feadc"
  },
  {
    "company_slug": "collins-aerospace",
    "company": "Collins Aerospace",
    "date": "02/03/2021",
    "effective_date": "02/26/2021",
    "region": "IA",
    "city": null,
    "workers": 5,
    "source_id": "rec8Uma5JH2wpfl3d",
    "id": "warn-c4293fa2faf78051"
  },
  {
    "company_slug": "chesapeake-energy",
    "company": "Chesapeake Energy",
    "date": "02/03/2021",
    "effective_date": "02/03/2021",
    "region": "OK",
    "city": null,
    "workers": 175,
    "source_id": "recFmODmjMYEn5Fwl",
    "id": "warn-31c94b19ec0da192"
  },
  {
    "company_slug": "lsg-sky-chefs",
    "company": "LSG Sky Chefs",
    "date": "02/03/2021",
    "effective_date": "02/03/2021",
    "region": "MI",
    "city": null,
    "workers": 375,
    "source_id": "rec6GLVMQydacKM7t",
    "id": "warn-5ea529ffbd535e09"
  },
  {
    "company_slug": "northern-sun",
    "company": "Northern Sun",
    "date": "02/03/2021",
    "effective_date": "02/03/2021",
    "region": "KS",
    "city": null,
    "workers": 30,
    "source_id": "rec06mmNp6aWgmIHk",
    "id": "warn-6f3e7d2d813e9e0e"
  },
  {
    "company_slug": "bluegrass-supply-chain-and-services",
    "company": "Bluegrass Supply Chain and Services",
    "date": "02/02/2021",
    "effective_date": "04/03/2021",
    "region": "KY",
    "city": null,
    "workers": 175,
    "source_id": "recAROyxfZhAmJ6OZ",
    "id": "warn-49a9da83f0a1f5f6"
  },
  {
    "company_slug": "kerry-group",
    "company": "Kerry Group",
    "date": "02/02/2021",
    "effective_date": "03/31/2021",
    "region": "IA",
    "city": null,
    "workers": 75,
    "source_id": "rectFVr4978NRfCrJ",
    "id": "warn-e2682be57b3f39f5"
  },
  {
    "company_slug": "purple-banana-–-mckenzie-pb",
    "company": "Purple Banana – McKenzie PB, LLC",
    "date": "02/02/2021",
    "effective_date": "01/31/2021",
    "region": "MS",
    "city": null,
    "workers": 5,
    "source_id": "recz2RVy8gmE65SWa",
    "id": "warn-9aeaccbe07c3756f"
  },
  {
    "company_slug": "hyatt",
    "company": "Hyatt",
    "date": "02/02/2021",
    "effective_date": "01/29/2021",
    "region": "CA",
    "city": null,
    "workers": 5,
    "source_id": "recevRj84NsXDx4jw",
    "id": "warn-775966298a5cc52a"
  },
  {
    "company_slug": "transform-sr",
    "company": "Transform SR LLC",
    "date": "02/02/2021",
    "effective_date": "02/02/2021",
    "region": "HI",
    "city": null,
    "workers": 5,
    "source_id": "recBICSMJhWpAoUnx",
    "id": "warn-8877a26525f8540d"
  },
  {
    "company_slug": "montage-kapalua-bay",
    "company": "Montage Kapalua Bay",
    "date": "02/02/2021",
    "effective_date": "02/02/2021",
    "region": "HI",
    "city": null,
    "workers": 5,
    "source_id": "rec1k2dmKy7mK1F7R",
    "id": "warn-3e10523dc77db431"
  },
  {
    "company_slug": "hawaiian-airlines",
    "company": "Hawaiian Airlines",
    "date": "02/02/2021",
    "effective_date": "02/02/2021",
    "region": "HI",
    "city": null,
    "workers": 5,
    "source_id": "recTpUYSPQxk87Tmi",
    "id": "warn-2c27bcd527ffebcb"
  },
  {
    "company_slug": "jtb-hawaii",
    "company": "JTB Hawaii, Inc.",
    "date": "02/02/2021",
    "effective_date": "02/02/2021",
    "region": "HI",
    "city": null,
    "workers": 5,
    "source_id": "recp7k01lq3nYgSnd",
    "id": "warn-6e1f61991d2892d6"
  },
  {
    "company_slug": "hawaii-his-corporation",
    "company": "Hawaii HIS Corporation",
    "date": "02/02/2021",
    "effective_date": "02/02/2021",
    "region": "HI",
    "city": null,
    "workers": 5,
    "source_id": "recKyAHDyIOAgMa4A",
    "id": "warn-7b676b217386e2ad"
  },
  {
    "company_slug": "quetico",
    "company": "Quetico LLC",
    "date": "02/01/2021",
    "effective_date": "04/10/2021",
    "region": "CA",
    "city": null,
    "workers": 375,
    "source_id": "recftMznhbCBWRFKv",
    "id": "warn-dab2dd1629561c40"
  },
  {
    "company_slug": "columbia-commercial-building-products",
    "company": "Columbia Commercial Building Products",
    "date": "02/01/2021",
    "effective_date": "04/02/2021",
    "region": "TX",
    "city": null,
    "workers": 75,
    "source_id": "reckf50TiQxKoAqa6",
    "id": "warn-2ffada3f70d89350"
  },
  {
    "company_slug": "royal-appliance-manufacturing-company-tti-floor-care-north-america",
    "company": "Royal Appliance Manufacturing Company (TTI Floor Care North America)",
    "date": "02/01/2021",
    "effective_date": "04/02/2021",
    "region": "OH",
    "city": null,
    "workers": 75,
    "source_id": "recMO4n7R7X0fDBo3",
    "id": "warn-9ecac6d4649bfb37"
  },
  {
    "company_slug": "uniqlo",
    "company": "Uniqlo",
    "date": "02/01/2021",
    "effective_date": "04/02/2021",
    "region": "CA",
    "city": null,
    "workers": 75,
    "source_id": "rechJPaipI0cwoxcE",
    "id": "warn-ef4671c335ba86b6"
  },
  {
    "company_slug": "coorstek-vista",
    "company": "CoorsTek Vista",
    "date": "02/01/2021",
    "effective_date": "04/02/2021",
    "region": "CA",
    "city": null,
    "workers": 30,
    "source_id": "recMnILeahVpnEdr9",
    "id": "warn-003ac996ad93eb33"
  },
  {
    "company_slug": "first-transit",
    "company": "First Transit",
    "date": "02/01/2021",
    "effective_date": "04/01/2021",
    "region": "VA",
    "city": null,
    "workers": 75,
    "source_id": "recJSYhkX5ruh3Y0U",
    "id": "warn-64f9f7932031af77"
  },
  {
    "company_slug": "ll-bean",
    "company": "LL Bean",
    "date": "02/01/2021",
    "effective_date": "02/01/2021",
    "region": "ME",
    "city": null,
    "workers": 5,
    "source_id": "recq3xaVCle4ytKC6",
    "id": "warn-e065c5249aa8e50b"
  },
  {
    "company_slug": "popular-bank",
    "company": "Popular Bank",
    "date": "02/01/2021",
    "effective_date": "02/01/2021",
    "region": "NJ",
    "city": null,
    "workers": 30,
    "source_id": "recUnbvZl5wYo1sgC",
    "id": "warn-9d351bf7278b09bf"
  },
  {
    "company_slug": "popular-bank",
    "company": "Popular Bank",
    "date": "02/01/2021",
    "effective_date": "02/01/2021",
    "region": "NJ",
    "city": null,
    "workers": 30,
    "source_id": "recmXAp2E5xYkvi4G",
    "id": "warn-425c2c3260bf221d"
  },
  {
    "company_slug": "coats-clark",
    "company": "Coats & Clark",
    "date": "02/01/2021",
    "effective_date": "02/01/2021",
    "region": "GA",
    "city": null,
    "workers": 175,
    "source_id": "recQGrl3fz1iYVgoS",
    "id": "warn-3f749889baa6be16"
  },
  {
    "company_slug": "allied-universal",
    "company": "Allied Universal",
    "date": "02/01/2021",
    "effective_date": "02/01/2021",
    "region": "MI",
    "city": null,
    "workers": 750,
    "source_id": "recW3UiRhqqgqAQ2x",
    "id": "warn-0e1123b8748a1ab8"
  },
  {
    "company_slug": "aon-corporation",
    "company": "AON Corporation",
    "date": "01/31/2021",
    "effective_date": "11/19/2018",
    "region": "IL",
    "city": null,
    "workers": 75,
    "source_id": "recNxxrx3SImCku6o",
    "id": "warn-3100a85237341740"
  },
  {
    "company_slug": "knotel",
    "company": "Knotel, Inc.",
    "date": "01/31/2021",
    "effective_date": "01/31/2021",
    "region": "NY",
    "city": null,
    "workers": 175,
    "source_id": "reckiPzy0kV0FuwW9",
    "id": "warn-25f6871f358bb938"
  },
  {
    "company_slug": "walmart",
    "company": "Walmart",
    "date": "01/31/2021",
    "effective_date": "01/31/2021",
    "region": "NJ",
    "city": null,
    "workers": 375,
    "source_id": "recsKLcnoIzCPNt06",
    "id": "warn-e691c073417355f8"
  },
  {
    "company_slug": "hackensack-meridian-health-long-term-care",
    "company": "Hackensack Meridian Health - Long Term Care",
    "date": "01/31/2021",
    "effective_date": "01/31/2021",
    "region": "NJ",
    "city": null,
    "workers": 175,
    "source_id": "recp6xbaDMyh0UeyF",
    "id": "warn-213f036916ea0e98"
  },
  {
    "company_slug": "canada-dry-bottling-company",
    "company": "Canada Dry Bottling Company",
    "date": "01/31/2021",
    "effective_date": "01/31/2021",
    "region": "NJ",
    "city": null,
    "workers": 30,
    "source_id": "recswimo9A4YZLDEk",
    "id": "warn-c51b8af0f58f3c17"
  },
  {
    "company_slug": "canada-dry-bottling-company",
    "company": "Canada Dry Bottling Company",
    "date": "01/31/2021",
    "effective_date": "01/31/2021",
    "region": "NJ",
    "city": null,
    "workers": 30,
    "source_id": "rechrBUmPnZbaRPA1",
    "id": "warn-719d6d7581de6de8"
  },
  {
    "company_slug": "geo-secure-services",
    "company": "GEO Secure Services LLC",
    "date": "01/30/2021",
    "effective_date": "03/31/2021",
    "region": "NC",
    "city": null,
    "workers": 375,
    "source_id": "recg78RQLPUf8VRdJ",
    "id": "warn-6f406e9968f9d3bc"
  },
  {
    "company_slug": "marelli-automotive",
    "company": "Marelli Automotive",
    "date": "01/30/2021",
    "effective_date": "01/30/2021",
    "region": "MI",
    "city": null,
    "workers": 375,
    "source_id": "recnNk4BOhElaT96h",
    "id": "warn-93f547a3246d333b"
  },
  {
    "company_slug": "mitsubishi-heavy-industries-climate-control",
    "company": "Mitsubishi Heavy Industries Climate Control",
    "date": "01/29/2021",
    "effective_date": "12/31/2021",
    "region": "IN",
    "city": null,
    "workers": 75,
    "source_id": "recyHMI0cehIqogLP",
    "id": "warn-32e64895dff622d7"
  },
  {
    "company_slug": "simple",
    "company": "Simple",
    "date": "01/29/2021",
    "effective_date": "06/11/2021",
    "region": "OR",
    "city": null,
    "workers": 30,
    "source_id": "recezCNFbE1NBS36V",
    "id": "warn-428b44b356b6c906"
  },
  {
    "company_slug": "phelps-dodge-industries-updated-notice",
    "company": "Phelps Dodge Industries (Updated Notice)",
    "date": "01/29/2021",
    "effective_date": "05/18/2021",
    "region": "CT",
    "city": null,
    "workers": 5,
    "source_id": "recFsM3RbUwscEEab",
    "id": "warn-c61a95156fec0d3c"
  },
  {
    "company_slug": "simple",
    "company": "Simple",
    "date": "01/29/2021",
    "effective_date": "05/14/2021",
    "region": "OR",
    "city": null,
    "workers": 75,
    "source_id": "reclzGcto8NfT7zca",
    "id": "warn-5c34642fe9f61f27"
  },
  {
    "company_slug": "simple",
    "company": "Simple",
    "date": "01/29/2021",
    "effective_date": "05/07/2021",
    "region": "OR",
    "city": null,
    "workers": 5,
    "source_id": "recVMPRv9aCdNRrIe",
    "id": "warn-b25223eae099f406"
  },
  {
    "company_slug": "paychex-north-america-incs-a-delaware-corporation",
    "company": "Paychex North America Inc.'s, a Delaware Corporation",
    "date": "01/29/2021",
    "effective_date": "04/19/2021",
    "region": "CA",
    "city": null,
    "workers": 30,
    "source_id": "recC4F6ivAsPcCaVC",
    "id": "warn-3298c82bbd34520b"
  },
  {
    "company_slug": "ralphs",
    "company": "Ralphs",
    "date": "01/29/2021",
    "effective_date": "04/17/2021",
    "region": "CA",
    "city": null,
    "workers": 75,
    "source_id": "recMaGDdhc0UA041U",
    "id": "warn-1278b8fa770fb5d6"
  },
  {
    "company_slug": "food-4-less",
    "company": "Food 4 Less",
    "date": "01/29/2021",
    "effective_date": "04/17/2021",
    "region": "CA",
    "city": null,
    "workers": 175,
    "source_id": "rec4ncFXQKEREpWEX",
    "id": "warn-8a4a8646aaa17a41"
  },
  {
    "company_slug": "food-4-less",
    "company": "Food 4 Less",
    "date": "01/29/2021",
    "effective_date": "04/17/2021",
    "region": "CA",
    "city": null,
    "workers": 75,
    "source_id": "rec87lfnNWSc2TERp",
    "id": "warn-b62b0f9d01062789"
  },
  {
    "company_slug": "bergeron-land-development",
    "company": "Bergeron Land Development, Inc.",
    "date": "01/29/2021",
    "effective_date": "04/07/2021",
    "region": "FL",
    "city": null,
    "workers": 30,
    "source_id": "recqA75uWUFsPrVKI",
    "id": "warn-8e75457dfef75973"
  },
  {
    "company_slug": "bergeron-land-development",
    "company": "Bergeron Land Development, Inc.",
    "date": "01/29/2021",
    "effective_date": "04/07/2021",
    "region": "FL",
    "city": null,
    "workers": 30,
    "source_id": "recrSmGSZUKoONe8V",
    "id": "warn-35ac2615d401412a"
  },
  {
    "company_slug": "bergeron-land-development",
    "company": "Bergeron Land Development, Inc.",
    "date": "01/29/2021",
    "effective_date": "04/07/2021",
    "region": "FL",
    "city": null,
    "workers": 30,
    "source_id": "recGLSzv0Mq5KoSEX",
    "id": "warn-e1a75a4661996dc4"
  },
  {
    "company_slug": "azlo",
    "company": "azlo",
    "date": "01/29/2021",
    "effective_date": "04/02/2021",
    "region": "OR",
    "city": null,
    "workers": 175,
    "source_id": "recjXaP1gdu1UIDEQ",
    "id": "warn-1f83e7c29c205f75"
  },
  {
    "company_slug": "simple",
    "company": "Simple",
    "date": "01/29/2021",
    "effective_date": "04/02/2021",
    "region": "OR",
    "city": null,
    "workers": 30,
    "source_id": "recLkwfgrr5uMcIgx",
    "id": "warn-e660a2a3605049b2"
  },
  {
    "company_slug": "wvc-rancho-mirage",
    "company": "WVC Rancho Mirage, Inc",
    "date": "01/29/2021",
    "effective_date": "04/02/2021",
    "region": "CA",
    "city": null,
    "workers": 30,
    "source_id": "reczEADeW8ZQ5lbBu",
    "id": "warn-5503b27e103bd75a"
  },
  {
    "company_slug": "vistana-california-management",
    "company": "Vistana California Management Inc",
    "date": "01/29/2021",
    "effective_date": "04/02/2021",
    "region": "CA",
    "city": null,
    "workers": 75,
    "source_id": "rec2GIghvjLkCUtoH",
    "id": "warn-9b4ed0719d5565ef"
  },
  {
    "company_slug": "upturn-business",
    "company": "Upturn Business Inc.",
    "date": "01/29/2021",
    "effective_date": "04/02/2021",
    "region": "CA",
    "city": null,
    "workers": 5,
    "source_id": "recbWgxT6ZYK3g1tR",
    "id": "warn-d5e268fd828e6d89"
  }
]
