{
  "slug": "jackson-county-memorial-hospital-authority",
  "canonical_name": "Jackson County Memorial Hospital Authority",
  "fein": "73-0568956",
  "lca_filing_count": 2,
  "warn_notice_count": 0,
  "median_wage_usd": 61235.0,
  "by_fy": [
    {
      "fy": 2025,
      "filings": 2,
      "median_wage_usd": 61235.0
    }
  ],
  "top_titles": [
    {
      "title": "Medical Technologist",
      "count": 1,
      "median_wage_usd": 56243.0
    },
    {
      "title": "Laboratory Supervisor (Medical Technologist)",
      "count": 1,
      "median_wage_usd": 66227.0
    }
  ],
  "top_counties": [],
  "top_states": [
    {
      "state": "OK",
      "count": 2
    }
  ],
  "warn_events": [],
  "uscis_h1b": {
    "initial_approvals": 3,
    "initial_denials": 0,
    "continuing_approvals": 0,
    "continuing_denials": 0,
    "total_approvals": 3,
    "by_fy": [
      {
        "fy": 2023,
        "initial_approvals": 3,
        "initial_denials": 0,
        "continuing_approvals": 0,
        "continuing_denials": 0,
        "total_approvals": 3
      }
    ]
  },
  "lca_worker_positions": 2,
  "top_socs": [],
  "lca_periods": []
}
