{
  "slug": "nogales-unified-school-district-no-1",
  "canonical_name": "Nogales Unified School District No. 1",
  "fein": null,
  "lca_filing_count": 1,
  "warn_notice_count": 0,
  "median_wage_usd": 47910.0,
  "by_fy": [
    {
      "fy": 2020,
      "filings": 1,
      "median_wage_usd": 47910.0
    }
  ],
  "top_titles": [
    {
      "title": "Teacher",
      "count": 1,
      "median_wage_usd": 47910.0
    }
  ],
  "top_counties": [
    {
      "state": "AZ",
      "county": "SANTA CRUZ",
      "count": 1
    }
  ],
  "top_states": [
    {
      "state": "AZ",
      "count": 1
    }
  ],
  "warn_events": [],
  "lca_worker_positions": 1,
  "top_socs": [],
  "lca_periods": []
}
