{
  "slug": "yotta-tech-ports",
  "canonical_name": "Yotta Tech Ports Inc.",
  "fein": "82-2412991",
  "lca_filing_count": 10,
  "lca_worker_positions": 10,
  "warn_notice_count": 0,
  "median_wage_usd": 128050.0,
  "by_fy": [
    {
      "fy": 2021,
      "filings": 2,
      "median_wage_usd": 125000.0
    },
    {
      "fy": 2022,
      "filings": 3,
      "median_wage_usd": 140000.0
    },
    {
      "fy": 2023,
      "filings": 3,
      "median_wage_usd": 120500.0
    },
    {
      "fy": 2025,
      "filings": 1,
      "median_wage_usd": 126100.0
    },
    {
      "fy": 2026,
      "filings": 1,
      "median_wage_usd": 160000.0,
      "through_quarter": 1
    }
  ],
  "top_titles": [
    {
      "title": "Sr Software Developer",
      "count": 3,
      "median_wage_usd": 122000.0
    },
    {
      "title": "Sr. Software Developer",
      "count": 2,
      "median_wage_usd": 135000.0
    },
    {
      "title": "Senior Solutions Architect",
      "count": 1,
      "median_wage_usd": 126100.0
    },
    {
      "title": "Software Developer",
      "count": 1,
      "median_wage_usd": 101200.0
    },
    {
      "title": "Principal Data Architect",
      "count": 1,
      "median_wage_usd": 160000.0
    },
    {
      "title": "Lead Data Engineer",
      "count": 1,
      "median_wage_usd": 120000.0
    },
    {
      "title": " Sr. Software Developer",
      "count": 1,
      "median_wage_usd": 140000.0
    }
  ],
  "top_counties": [
    {
      "state": "TX",
      "county": "DALLAS",
      "count": 3
    },
    {
      "state": "VA",
      "county": "HENRICO",
      "count": 1
    },
    {
      "state": "TX",
      "county": "COLLIN",
      "count": 1
    },
    {
      "state": "VA",
      "county": "HANOVER",
      "count": 1
    },
    {
      "state": "NC",
      "county": "UNION",
      "count": 1
    },
    {
      "state": "NC",
      "county": "MECKLENBURG",
      "count": 1
    }
  ],
  "top_states": [
    {
      "state": "TX",
      "count": 4
    },
    {
      "state": "VA",
      "count": 4
    },
    {
      "state": "NC",
      "count": 2
    }
  ],
  "warn_events": [],
  "top_socs": [],
  "lca_periods": [],
  "bls_benchmark": {
    "soc_code": "15-1252",
    "soc_title": "Software Developers",
    "market_median_usd": 130160.0,
    "employer_median_usd": 124050.0,
    "gap_usd": -6110.0
  }
}
